smac_fastapi_auth/__init__.py
smac_fastapi_auth/automation/__init__.py
smac_fastapi_auth/automation/sec_mgr_helper.py
smac_fastapi_auth/automation/settings.py
smac_fastapi_auth/cognito/__init__.py
smac_fastapi_auth/cognito/jwt_helper.py
smac_fastapi_auth/cognito/settings.py
smac_fastapi_auth/core/__init__.py
smac_fastapi_auth/core/constants.py
smac_fastapi_auth/core/provider_helper.py
smac_fastapi_auth/core/settings.py
smac_fastapi_auth/models/__init__.py
smac_fastapi_auth/models/context.py
smac_fastapi_auth/models/principal.py
smac_fastapi_auth/services/__init__.py
smac_fastapi_auth/services/auth.py
smac_fastapi_auth/setup.py
smac_fastapi_auth-0.4.1.dist-info/LICENSE
smac_fastapi_auth-0.4.1.dist-info/METADATA
smac_fastapi_auth-0.4.1.dist-info/WHEEL
smac_fastapi_auth-0.4.1.dist-info/RECORD
