Metadata-Version: 2.1
Name: smac-fastapi-auth
Version: 0.4.1
Summary: Reusable code for authentication in Python backends using FastAPI
License: Apache-2.0
Author: Sven Maschek
Author-email: dev@smaschek.com
Requires-Python: >=3.12,<4.0
Classifier: License :: OSI Approved :: Apache Software License
Classifier: Programming Language :: Python :: 3
Classifier: Programming Language :: Python :: 3.12
Classifier: Programming Language :: Python :: 3.13
Requires-Dist: aiohttp (>=3.11.11,<4.0.0)
Requires-Dist: boto3 (>=1.35.90,<2.0.0)
Requires-Dist: cachebox (>=3.2.1,<4.0.0)
Requires-Dist: fastapi-cognito (>=2.7.0,<3.0.0)
Requires-Dist: loguru (>=0.7.3,<0.8.0)
Requires-Dist: pydantic-settings (>=2.7.0,<3.0.0)
